<PAMDataset>
  <PAMRasterBand band="1">
    <Histograms>
      <HistItem>
        <HistMin>-7.1495</HistMin>
        <HistMax>14306.1495</HistMax>
        <BucketCount>1000</BucketCount>
        <IncludeOutOfRange>0</IncludeOutOfRange>
        <Approximate>0</Approximate>
        <HistCounts>185271|0|0|0|0|0|0|0|0|0|0|0|0|0|0|0|0|0|0|0|0|0|0|0|0|0|0|0|0|0|0|0|0|0|0|0|0|0|0|0|0|0|0|0|0|0|0|0|0|0|0|0|0|0|0|0|0|0|0|0|0|0|0|0|0|0|0|0|0|0|1|5|24|52|86|122|106|118|76|91|103|65|48|34|35|25|37|31|32|26|19|15|19|35|28|22|25|32|32|25|32|33|28|34|29|24|30|43|34|45|36|59|64|53|54|64|51|65|64|55|90|75|79|78|71|78|86|78|55|59|55|38|33|32|29|22|23|27|21|15|18|13|17|12|17|18|12|18|27|18|14|16|14|23|16|21|28|36|51|62|66|110|128|201|208|217|243|229|280|289|260|264|307|299|290|265|296|263|302|330|236|265|263|250|264|284|238|286|296|237|270|252|262|229|215|214|175|191|182|154|167|191|156|148|174|132|134|124|131|113|110|112|103|104|101|116|86|94|88|74|85|80|74|83|52|80|55|82|70|64|62|65|66|74|66|67|62|76|64|78|74|80|85|67|69|53|88|57|72|68|57|71|80|60|73|65|65|48|61|85|55|63|61|64|62|78|43|72|86|63|65|80|81|50|76|64|79|77|95|69|60|83|65|53|76|73|56|74|64|80|91|73|91|64|78|88|85|78|86|76|111|87|74|87|75|97|96|87|71|89|103|107|96|113|102|113|129|103|125|105|131|133|155|122|108|135|141|127|128|141|123|137|133|151|137|143|165|146|165|129|154|165|188|147|140|167|164|170|177|178|186|199|191|198|202|206|187|199|221|203|202|210|209|199|191|214|190|233|226|229|239|222|231|271|242|253|259|266|246|270|288|255|262|258|260|253|292|281|262|298|280|320|290|326|292|284|327|310|319|342|328|307|351|341|331|374|323|325|368|336|341|327|373|345|332|375|348|367|383|337|352|372|374|361|401|330|386|376|414|397|366|392|377|342|406|335|390|382|405|363|383|371|372|381|405|394|351|364|390|403|421|403|392|406|369|359|420|392|419|415|445|382|398|439|374|375|453|374|374|433|440|418|436|422|425|398|439|381|442|443|409|451|463|432|433|442|435|453|478|435|419|399|467|492|390|521|466|436|485|418|457|469|471|456|460|444|441|455|461|386|432|493|504|511|468|479|476|530|518|454|523|530|489|496|483|476|490|544|478|441|498|489|518|509|443|500|461|456|474|512|487|408|483|520|402|459|478|446|440|483|444|457|461|415|485|500|475|431|451|488|434|470|466|434|391|435|404|396|412|376|429|447|377|414|392|436|437|439|431|444|422|435|400|406|448|386|350|403|374|388|374|353|306|350|331|332|303|296|268|289|281|270|247|279|244|228|290|275|226|243|217|239|241|259|202|223|214|209|204|232|211|217|226|245|197|179|201|182|176|217|201|185|201|189|185|198|198|173|200|202|164|182|176|202|178|179|182|186|174|172|159|168|162|164|173|134|156|157|132|141|130|150|159|171|165|142|148|162|165|150|179|138|144|177|130|127|130|156|151|127|145|158|120|114|134|147|125|108|119|116|116|124|114|131|109|115|125|101|98|106|118|108|99|120|128|104|95|82|82|121|86|113|96|105|102|103|98|106|122|103|90|75|87|92|80|91|81|81|104|88|100|105|90|83|120|80|97|104|80|93|81|76|77|77|79|63|73|78|93|59|76|59|55|71|54|63|63|51|61|68|66|71|55|54|66|67|69|55|64|61|56|46|58|55|47|46|57|54|47|61|48|54|53|48|56|56|54|54|42|47|36|43|48|42|45|54|29|53|55|44|26|35|33|43|39|36|39|34|38|28|47|45|36|32|40|36|34|46|35|31|41|29|27|28|27|28|30|32|29|23|24|26|22|33|23|21|32|24|25|26|24|23|30|23|31|14|26|27|19|19|20|15|12|15|15|16|14|11|12|24|13|21|14|11|18|10|6|10|10|15|8|9|11|10|10|18|10|9|13|9|7|9|7|11|6|9|8|12|7|3|6|4|9|5|8|8|6|10|7|3|8|9|6|8|4|9|3|6|3|2|2|3|10|2|3|4|4|5|5|7|3|1|4|3|1|3|2|2|4|7|2|1|5|6|4|2|2|1|4|2|2|2|5|0|2|1|4|1|2|4|1|0|6|1|3|2|2|1|3|4|2|1|2|2|1|3|0|0|2|2|2|0|2|2|4|3|2|1|0|1|2|0|1|1|1|3|0|0|2|1|0|0|0|3|1|1|0|1|0|1</HistCounts>
      </HistItem>
    </Histograms>
    <Metadata>
      <MDI key="STATISTICS_MAXIMUM">14299</MDI>
      <MDI key="STATISTICS_MEAN">3044.9127628324</MDI>
      <MDI key="STATISTICS_MINIMUM">0</MDI>
      <MDI key="STATISTICS_STDDEV">3692.7753327324</MDI>
      <MDI key="STATISTICS_VALID_PERCENT">100</MDI>
    </Metadata>
  </PAMRasterBand>
  <PAMRasterBand band="2">
    <Histograms>
      <HistItem>
        <HistMin>-7.5975</HistMin>
        <HistMax>15202.5975</HistMax>
        <BucketCount>1000</BucketCount>
        <IncludeOutOfRange>0</IncludeOutOfRange>
        <Approximate>0</Approximate>
        <HistCounts>185271|0|0|0|0|0|0|0|0|0|0|0|0|0|0|0|12|19|16|50|53|55|73|111|68|103|64|68|72|36|50|40|66|69|51|50|64|25|44|24|33|48|29|51|65|57|35|52|52|59|60|56|69|72|60|118|133|96|148|160|144|222|188|305|269|325|318|326|271|269|258|232|241|240|261|222|223|306|262|238|259|277|314|311|260|230|277|225|288|195|220|285|182|184|191|235|170|140|128|114|140|180|157|165|148|149|97|116|118|108|111|121|108|107|132|101|133|69|69|38|63|69|98|91|91|83|59|52|73|24|87|40|64|101|73|59|50|88|65|56|57|56|50|33|45|54|54|59|44|75|48|58|71|52|56|70|28|46|36|75|68|50|31|65|78|73|53|74|84|40|45|30|59|63|47|50|58|54|64|68|85|49|50|58|29|70|48|82|46|59|41|52|55|83|80|80|68|56|82|99|49|85|72|59|66|105|64|73|52|58|94|77|72|100|95|48|64|100|60|70|54|94|70|91|95|60|90|75|93|141|82|98|73|102|75|108|83|83|72|94|128|126|123|89|67|120|106|100|96|133|123|124|98|82|104|117|151|98|133|150|117|111|159|155|158|168|132|109|138|152|165|194|190|139|174|172|170|144|156|241|181|190|140|191|196|184|190|167|176|156|195|193|167|238|167|178|199|166|216|190|215|192|226|236|205|231|226|243|239|195|261|226|249|231|296|252|274|213|247|217|243|238|244|267|238|253|232|285|283|289|311|307|261|287|234|293|296|275|313|261|250|264|288|337|349|435|375|341|278|365|359|305|291|299|333|314|269|282|313|266|310|328|305|340|294|324|282|289|342|377|360|272|322|382|302|374|255|379|370|345|308|331|262|404|330|315|333|304|344|376|316|343|399|346|302|293|383|403|399|334|392|359|427|276|298|324|287|439|428|336|348|355|358|358|338|332|424|397|402|379|304|303|343|296|356|336|392|310|379|362|390|433|367|336|357|398|482|407|393|358|348|314|360|377|385|436|416|403|358|378|381|393|350|360|451|402|317|418|406|365|404|415|378|370|490|391|402|341|418|489|398|388|430|463|398|409|406|426|434|389|330|371|386|429|348|365|447|427|433|502|376|456|410|377|412|412|429|453|368|322|343|322|451|419|359|369|354|417|407|380|385|393|393|337|330|430|438|257|310|363|386|372|351|428|346|350|407|382|305|348|377|344|315|332|402|353|312|324|391|308|305|351|302|314|320|413|360|342|346|346|386|324|301|369|295|280|297|240|295|341|312|303|294|289|205|254|227|197|237|239|251|252|179|235|258|207|194|203|198|188|208|252|189|229|215|245|246|218|185|195|135|187|236|166|199|179|227|249|177|124|136|165|239|154|184|131|162|259|224|120|216|160|149|145|187|196|141|158|188|216|132|177|140|170|114|143|157|140|136|132|151|158|112|174|162|163|163|148|163|150|140|151|163|120|149|188|106|140|134|171|143|124|130|166|129|125|88|111|158|88|95|100|146|137|94|117|101|129|120|100|131|138|115|116|50|95|77|137|84|107|82|95|96|92|115|125|84|100|105|113|96|120|102|68|83|105|66|75|67|66|74|87|98|56|91|76|87|76|67|51|76|98|105|98|80|94|84|79|53|102|74|63|89|46|63|100|64|88|91|40|84|53|68|80|59|56|52|40|72|42|27|75|72|56|26|84|69|64|79|60|50|52|24|72|54|34|68|66|47|40|55|54|28|105|38|27|40|36|59|87|36|59|28|74|52|50|36|49|49|48|38|20|42|40|32|36|16|40|31|49|44|37|43|36|28|58|20|32|34|48|36|45|44|31|38|12|30|12|28|32|24|19|26|35|36|22|35|34|24|20|44|29|20|36|23|18|35|46|23|13|36|32|40|21|12|16|24|16|20|8|16|32|31|20|16|8|17|0|16|12|9|24|10|22|16|16|20|10|8|20|8|12|16|15|12|16|8|17|8|20|12|20|4|4|16|12|4|0|8|8|8|0|4|4|8|8|16|4|10|4|4|4|12|4|4|0|0|4|8|4|8|0|8|7|1|0|0|4|3|0|8|8|4|0|0|4|4|8|3|0|0|8|8|0|0|8|0|4|0|0|4|0|0|0|1|3|0|0|4|8|0|4|0|0|0|0|4|0|0|2|4|0|0|0|0|4|0|0|3|0|4|0|0|0|0|4|0|4|4|0|0|4|0|0|0|8|4|4|4|0|4|4|4|0|0|4|0|0|0|0|0|4|0|0|0|0|0|4|0|4</HistCounts>
      </HistItem>
    </Histograms>
    <Metadata>
      <MDI key="STATISTICS_MAXIMUM">15195</MDI>
      <MDI key="STATISTICS_MEAN">2880.4171126493</MDI>
      <MDI key="STATISTICS_MINIMUM">0</MDI>
      <MDI key="STATISTICS_STDDEV">3665.9457199678</MDI>
      <MDI key="STATISTICS_VALID_PERCENT">100</MDI>
    </Metadata>
  </PAMRasterBand>
  <PAMRasterBand band="3">
    <Histograms>
      <HistItem>
        <HistMin>-7.599</HistMin>
        <HistMax>15205.599</HistMax>
        <BucketCount>1000</BucketCount>
        <IncludeOutOfRange>0</IncludeOutOfRange>
        <Approximate>0</Approximate>
        <HistCounts>185271|0|0|0|0|0|0|0|0|0|0|0|0|0|0|0|1|4|16|31|51|69|112|140|138|103|80|62|34|46|67|62|49|42|36|30|27|26|25|24|40|41|41|49|60|52|46|49|45|57|60|78|60|87|90|92|87|77|86|137|175|185|214|276|292|310|308|297|349|279|286|247|263|301|291|259|237|290|279|250|298|293|323|306|292|296|271|309|305|260|243|257|241|252|209|197|196|176|197|172|171|174|178|159|138|134|124|119|130|119|112|108|113|102|98|96|101|101|89|65|83|82|67|51|72|65|63|67|69|90|69|63|56|65|71|72|56|61|61|69|56|47|52|67|62|51|61|50|48|56|49|75|56|56|71|52|46|53|54|52|56|48|53|63|55|49|67|52|62|57|65|40|50|64|54|58|51|43|68|46|51|57|71|56|54|54|70|62|67|49|75|58|84|60|67|68|79|65|75|76|74|62|62|70|67|78|57|69|63|68|74|71|68|80|75|79|81|69|73|77|65|75|92|88|100|84|90|108|103|102|102|122|92|109|115|99|116|105|94|105|97|105|105|122|111|100|103|105|111|124|128|131|125|131|121|158|148|130|141|149|131|156|127|125|135|169|137|127|158|150|169|160|152|153|183|163|167|151|158|182|159|180|182|155|182|201|194|187|204|188|186|191|195|205|187|211|201|246|214|194|224|212|220|259|233|228|256|253|241|233|221|235|268|245|257|221|251|269|270|220|268|273|283|259|256|282|279|271|256|277|284|347|280|254|267|310|285|289|303|286|350|334|295|285|314|311|308|324|263|325|295|332|332|302|352|317|310|349|321|302|299|357|312|320|307|319|335|320|316|341|302|295|319|327|352|328|323|317|341|316|331|330|375|350|321|325|329|381|337|282|344|326|384|343|350|349|346|356|349|352|353|357|359|345|355|331|358|338|376|373|360|353|356|341|351|383|352|362|360|323|381|340|376|351|387|378|346|384|359|384|332|369|343|381|391|356|370|374|374|361|356|371|340|405|396|358|400|383|394|371|371|384|352|432|385|388|383|406|400|406|383|390|435|408|354|409|413|402|446|423|401|405|439|425|432|398|435|384|403|386|392|475|425|426|406|410|375|438|430|363|398|392|401|429|368|435|414|397|349|366|401|378|344|383|411|378|411|372|391|389|397|388|399|388|426|370|417|391|371|344|351|362|342|383|356|359|327|354|354|314|349|344|362|340|368|353|389|356|373|357|358|375|373|337|346|339|363|314|344|338|319|305|291|293|319|276|315|260|279|284|257|273|233|228|246|255|207|224|209|208|217|214|227|197|190|236|236|179|207|204|192|197|178|200|238|185|196|212|197|184|190|177|179|186|190|179|202|184|156|158|171|172|160|177|190|166|177|172|155|156|161|169|183|127|155|185|157|176|175|150|150|146|167|147|137|155|146|119|124|118|135|152|130|144|115|132|168|125|137|159|144|140|135|154|138|159|137|133|145|122|139|111|114|128|123|131|118|106|115|138|88|116|109|105|131|106|106|96|102|105|100|95|89|118|104|92|91|109|93|88|93|82|108|98|83|75|92|113|81|84|92|90|98|84|80|80|100|79|88|82|87|83|88|78|75|85|88|72|93|75|76|92|78|73|90|75|81|74|71|76|78|82|63|63|67|68|73|63|57|66|53|66|59|69|53|51|43|48|50|59|51|62|48|50|46|54|49|70|51|50|53|62|52|54|56|40|37|46|51|43|54|48|48|44|53|46|47|45|55|37|47|42|42|46|46|44|49|34|53|38|38|50|21|37|34|40|37|39|32|35|39|41|37|28|31|35|44|27|33|27|38|28|32|43|32|40|34|28|33|24|25|30|35|28|38|27|24|31|43|25|19|25|20|17|29|26|25|20|26|16|22|17|21|25|25|17|24|25|15|20|22|17|22|17|32|22|16|17|21|15|16|15|10|9|12|5|7|15|15|14|18|9|10|9|16|12|12|11|7|8|14|8|6|11|13|8|3|4|9|5|7|6|4|7|5|5|6|11|5|5|7|8|5|6|9|5|8|4|5|8|3|6|3|5|5|4|3|1|7|3|1|4|6|4|2|2|3|3|1|4|6|3|1|5|2|6|6|6|4|4|3|2|2|2|1|5|2|3|3|3|2|1|2|1|2|0|3|1|2|2|2|0|2|3|0|0|4|2|2|3|2|1|3|1|2|1|1|3|1|3|4|1|1|1|1|2|1|1|2|2|4|1|2|0|0|0|3|4|0|0|0|0|1|1|1|2|0|1|0|2</HistCounts>
      </HistItem>
    </Histograms>
    <Metadata>
      <MDI key="STATISTICS_MAXIMUM">15198</MDI>
      <MDI key="STATISTICS_MEAN">2848.6973859474</MDI>
      <MDI key="STATISTICS_MINIMUM">0</MDI>
      <MDI key="STATISTICS_STDDEV">3637.2114226352</MDI>
      <MDI key="STATISTICS_VALID_PERCENT">100</MDI>
    </Metadata>
  </PAMRasterBand>
</PAMDataset>
