<PAMDataset>
  <PAMRasterBand band="1">
    <Histograms>
      <HistItem>
        <HistMin>-5.8555</HistMin>
        <HistMax>11716.8555</HistMax>
        <BucketCount>1000</BucketCount>
        <IncludeOutOfRange>0</IncludeOutOfRange>
        <Approximate>0</Approximate>
        <HistCounts>247025|0|0|0|0|0|0|0|0|0|0|0|0|0|0|0|0|0|0|0|0|0|0|0|0|0|0|0|0|0|0|0|0|0|0|0|0|0|0|0|0|0|0|0|0|0|0|0|0|0|0|0|0|0|0|0|1|14|24|42|34|29|46|52|70|71|102|87|73|53|51|57|42|49|38|49|40|55|41|48|48|49|43|48|38|65|70|63|82|87|96|95|108|103|120|131|162|150|212|226|243|198|323|341|349|338|369|379|379|423|418|477|453|496|547|510|602|581|593|517|619|639|614|578|610|618|596|593|582|590|489|533|517|444|510|472|460|420|468|453|422|379|396|384|364|386|393|414|357|397|383|330|339|358|341|346|355|310|323|307|337|320|240|333|313|265|248|268|261|247|249|215|246|228|226|265|251|226|248|236|213|214|253|232|212|207|198|238|215|214|238|202|238|235|226|217|232|252|221|237|249|239|195|219|221|217|205|273|209|193|231|240|212|213|233|245|222|238|224|224|201|219|226|236|220|220|201|207|229|259|228|204|226|250|206|253|208|232|210|250|243|234|209|243|237|214|217|249|244|206|220|228|221|254|222|267|184|228|238|231|218|226|248|237|235|244|242|227|254|248|239|252|232|250|216|266|226|255|213|229|268|259|238|272|218|241|240|269|263|210|247|258|214|251|236|235|217|233|272|241|258|223|250|254|210|244|240|226|249|250|232|251|227|242|206|232|227|213|233|216|205|207|230|253|243|188|213|232|194|227|209|200|212|195|229|175|210|209|241|206|224|234|207|206|218|215|178|215|210|233|186|219|214|172|209|221|207|207|236|216|210|179|210|220|203|225|206|219|229|226|204|198|223|220|226|207|261|251|235|216|251|236|205|201|264|233|205|219|262|251|220|246|219|213|275|237|237|232|264|233|224|256|248|228|220|263|252|211|200|254|238|237|254|252|265|206|276|264|258|272|291|259|233|241|264|262|249|279|297|254|285|267|268|245|273|253|245|300|267|237|260|247|290|233|274|285|280|231|304|283|272|250|268|263|239|298|299|284|293|290|302|284|266|277|295|263|305|277|314|278|280|286|291|284|307|283|263|321|290|261|251|266|298|243|260|262|273|230|238|283|247|295|236|276|229|305|283|248|257|281|256|244|271|262|262|245|266|270|291|246|278|234|214|254|247|254|238|265|275|216|241|235|241|225|230|243|239|222|280|241|241|222|220|249|217|234|239|229|223|231|239|203|212|253|225|226|233|233|240|234|219|249|213|245|217|188|213|235|231|190|231|232|234|209|222|213|204|222|224|229|192|219|248|213|240|232|239|195|208|245|211|204|210|223|226|232|225|232|188|238|218|201|228|215|224|183|201|209|195|196|174|172|158|184|178|184|147|180|181|169|183|164|181|158|174|146|172|148|161|159|125|142|147|130|143|126|139|125|116|111|112|104|104|104|100|85|103|93|99|102|77|76|59|77|96|75|80|80|84|70|55|57|65|66|68|57|52|50|44|59|39|42|51|46|33|48|56|38|43|48|34|31|49|36|30|33|31|36|28|33|41|41|27|30|26|24|22|28|32|23|24|25|13|29|29|32|30|23|21|33|24|23|18|22|24|26|21|26|26|23|23|18|13|34|17|19|10|19|19|21|17|26|20|22|18|11|27|18|14|21|22|11|17|13|18|25|19|18|22|12|20|20|20|12|14|15|22|15|26|14|14|29|21|16|10|19|19|16|23|16|14|17|15|20|22|21|21|13|16|14|18|13|13|19|19|18|12|17|18|11|4|14|16|17|19|17|9|18|16|11|10|13|12|16|16|14|11|18|23|15|16|9|21|10|18|21|16|13|18|15|24|18|18|25|19|18|22|13|22|16|18|17|11|12|19|11|9|22|16|23|9|17|13|18|24|16|18|15|18|11|25|19|20|18|15|22|22|28|13|18|23|21|14|32|24|23|17|20|24|17|31|27|25|28|22|19|15|23|22|19|25|21|20|16|23|23|24|21|18|21|15|14|17|17|18|16|12|20|21|13|18|18|14|12|13|11|15|10|14|10|15|13|12|14|20|18|18|16|8|14|16|10|15|19|11|15|16|13|19|14|19|16|20|16|8|15|8|3|13|16|8|11|12|5|8|6|9|15|14|11|12|12|11|5|13|11|13|17|15|12|13|11|8|11|8|10|9|8|8|2|6|10|3|4|3|3|3|4|6|1|5|8|8|5|4|7|5|2|4|2|1|0|3|2|2|1|1|0|2|2|1|1|0|0|1|0|0|0|0|1</HistCounts>
      </HistItem>
    </Histograms>
    <Metadata>
      <MDI key="STATISTICS_MAXIMUM">11711</MDI>
      <MDI key="STATISTICS_MEAN">1561.7941962475</MDI>
      <MDI key="STATISTICS_MINIMUM">0</MDI>
      <MDI key="STATISTICS_STDDEV">2414.0051728526</MDI>
      <MDI key="STATISTICS_VALID_PERCENT">100</MDI>
    </Metadata>
  </PAMRasterBand>
  <PAMRasterBand band="2">
    <Histograms>
      <HistItem>
        <HistMin>-5.0095</HistMin>
        <HistMax>10024.0095</HistMax>
        <BucketCount>1000</BucketCount>
        <IncludeOutOfRange>0</IncludeOutOfRange>
        <Approximate>0</Approximate>
        <HistCounts>247025|0|0|0|0|0|0|0|0|0|0|0|0|0|0|0|8|36|38|43|42|64|33|47|63|47|29|70|53|59|52|59|47|48|48|6|75|57|86|90|99|87|101|113|116|131|135|167|169|166|160|280|227|150|193|148|233|209|139|175|140|131|146|173|193|200|152|174|159|184|180|158|172|214|187|185|192|154|179|228|181|231|211|192|213|254|237|223|212|233|294|264|267|339|284|304|274|324|311|369|315|338|250|367|249|283|366|252|315|287|401|352|342|361|291|302|327|376|341|375|360|318|358|332|334|435|307|450|292|321|333|331|350|349|315|388|380|351|360|356|321|323|292|303|302|306|333|204|325|234|260|298|322|289|263|336|313|280|280|290|276|280|284|263|279|272|206|247|265|275|249|255|389|294|287|241|275|221|264|260|209|256|252|204|254|282|259|259|243|271|249|264|260|223|251|216|230|209|263|208|242|249|191|282|255|232|249|313|216|251|256|231|216|252|210|258|210|179|230|218|251|186|233|228|202|244|262|254|226|227|255|252|235|196|220|253|249|292|281|241|262|230|250|290|279|209|245|207|251|240|283|213|343|292|244|263|224|226|242|259|269|209|178|219|242|308|240|222|284|231|282|232|230|232|205|262|268|190|217|228|150|235|245|214|216|257|256|260|259|253|182|238|240|232|245|227|221|195|234|179|196|198|240|198|161|214|194|210|223|187|212|201|189|232|149|221|236|206|214|215|178|193|214|223|185|220|232|225|193|220|217|171|182|176|136|207|258|154|195|184|158|178|163|190|223|162|162|216|182|185|150|207|185|241|219|167|166|187|148|221|209|145|181|209|182|240|204|211|196|226|177|227|230|240|226|225|214|190|183|244|191|196|174|215|228|205|186|209|199|195|172|182|259|232|180|168|198|255|247|244|216|207|201|194|223|287|191|174|245|213|210|226|224|240|290|175|302|238|254|255|217|283|282|234|210|255|232|238|298|230|259|215|280|215|206|216|220|222|266|222|248|219|179|166|288|285|239|237|213|231|233|202|237|230|232|230|238|240|290|243|253|284|265|298|274|223|292|280|275|273|256|231|224|220|235|253|275|224|291|301|281|204|332|226|236|235|273|269|234|288|228|316|215|214|219|284|253|281|204|219|250|321|315|257|266|222|268|186|251|174|225|251|239|241|222|172|245|346|228|219|218|225|250|230|242|189|218|157|155|174|237|199|160|186|189|191|209|184|204|214|128|223|176|186|182|143|199|159|148|180|168|171|144|111|136|202|176|102|157|157|176|194|148|190|180|192|146|172|178|138|204|158|191|124|144|176|136|154|142|152|146|167|163|266|166|158|169|115|198|158|204|200|172|196|203|165|198|174|202|192|192|178|166|182|137|238|135|212|138|190|207|167|178|218|208|176|211|108|153|134|135|140|174|174|153|146|147|152|196|144|154|188|158|119|200|114|140|172|118|188|114|180|134|120|98|156|120|125|166|150|164|115|115|82|151|118|138|114|147|168|84|104|100|59|66|80|100|64|72|66|58|74|90|90|66|81|57|64|74|82|44|52|65|62|66|64|54|54|40|66|66|34|36|36|42|82|37|56|52|54|34|50|31|40|38|32|32|20|36|60|35|36|42|30|48|23|29|40|36|44|26|18|20|32|20|38|16|60|52|44|42|12|12|20|24|20|20|32|46|12|20|16|8|12|8|20|18|16|47|16|16|16|32|20|23|16|18|17|10|32|20|16|12|29|12|20|15|34|28|6|24|20|19|16|16|28|16|17|21|24|15|8|8|48|20|8|22|18|16|16|28|24|20|8|4|24|8|24|12|14|8|22|8|14|8|4|32|4|18|4|22|4|12|28|16|18|8|24|20|26|10|16|12|19|4|8|16|14|8|32|12|20|32|28|16|0|12|28|3|23|16|16|8|8|8|26|19|11|28|16|16|4|20|4|12|20|10|16|56|8|20|30|12|12|4|20|12|4|16|17|24|22|8|20|16|20|20|24|14|24|16|4|24|8|32|40|28|12|18|20|42|28|28|27|16|30|44|0|12|16|20|24|16|16|20|28|16|22|16|28|8|20|24|16|38|16|12|16|8|8|16|21|16|8|20|24|12|23|25|20|4|28|17|4|4|26|20|20|5|36|13|12|15|0|12|12|12|26|4|30|17|16|8|16|8|32|12|9|8|16|18|16|9|8|4|16|16|3|12|16|16|8|18|13|16|4|14|4|9|0|0|8|4|9|4|8|0|4|0|4|0|12|8|0|0|0|0|4|0|4</HistCounts>
      </HistItem>
    </Histograms>
    <Metadata>
      <MDI key="STATISTICS_MAXIMUM">10019</MDI>
      <MDI key="STATISTICS_MEAN">1313.1928448276</MDI>
      <MDI key="STATISTICS_MINIMUM">0</MDI>
      <MDI key="STATISTICS_STDDEV">2092.83787749</MDI>
      <MDI key="STATISTICS_VALID_PERCENT">100</MDI>
    </Metadata>
  </PAMRasterBand>
  <PAMRasterBand band="3">
    <Histograms>
      <HistItem>
        <HistMin>-5.157</HistMin>
        <HistMax>10319.157</HistMax>
        <BucketCount>1000</BucketCount>
        <IncludeOutOfRange>0</IncludeOutOfRange>
        <Approximate>0</Approximate>
        <HistCounts>247025|0|0|0|0|0|0|0|0|0|0|0|0|0|0|0|0|0|12|41|69|68|59|49|45|70|61|87|78|80|70|55|44|37|56|57|53|62|64|81|82|78|124|129|124|122|171|173|159|176|226|210|228|187|205|216|232|199|201|213|217|197|202|190|186|231|179|202|218|202|179|238|196|217|255|236|210|256|261|230|271|260|276|334|247|269|363|320|316|355|346|342|370|369|350|330|344|328|327|382|368|388|348|328|331|377|347|368|371|404|337|381|375|361|378|324|342|396|351|356|374|338|349|390|342|380|370|330|339|379|345|342|357|360|325|322|380|306|297|343|293|277|347|267|277|331|265|275|302|263|284|279|245|274|268|269|276|263|232|245|268|239|238|271|211|236|262|228|233|268|254|240|232|256|234|212|264|207|230|241|224|206|265|250|228|231|200|215|250|218|226|251|212|212|228|243|230|234|221|215|241|233|223|239|238|228|231|214|263|245|254|220|197|247|251|214|242|222|254|250|219|233|221|209|234|238|198|235|271|217|227|242|217|255|262|239|261|255|202|229|267|237|236|237|274|246|222|225|208|260|243|243|226|264|266|271|222|262|241|253|199|227|271|233|226|286|217|236|259|249|218|251|255|250|281|246|246|252|201|222|226|251|229|211|248|212|206|242|209|215|208|209|212|198|224|234|213|189|214|216|221|191|231|192|204|202|237|194|221|191|222|235|240|231|210|178|171|185|196|206|210|213|206|232|178|174|196|198|179|216|223|179|197|194|222|201|217|184|183|192|190|169|207|187|162|212|197|187|209|169|188|191|187|209|215|223|183|181|208|198|181|168|189|205|200|201|194|216|198|164|206|207|195|200|195|222|204|192|199|212|191|211|239|207|234|245|193|203|242|220|222|207|257|228|224|262|207|243|234|218|233|213|251|246|261|211|236|264|246|211|244|225|223|227|220|242|246|245|234|262|235|230|230|236|242|244|236|230|240|252|242|224|262|246|234|251|244|219|274|225|257|280|236|241|250|229|239|292|271|245|261|267|234|273|246|238|273|276|252|268|242|213|276|249|269|231|286|262|253|282|224|235|298|242|250|287|269|221|298|261|233|282|228|235|225|230|218|291|272|238|222|234|221|284|233|256|255|237|251|212|260|213|203|234|229|200|241|207|221|225|215|235|220|229|215|223|220|199|233|182|226|214|177|213|221|177|185|217|194|190|213|189|204|222|162|184|181|206|191|166|189|192|175|188|177|171|177|153|161|173|163|157|189|165|148|176|150|159|187|173|167|173|160|173|176|187|168|159|164|185|199|192|179|174|201|183|202|189|185|177|209|193|169|195|197|198|209|187|188|172|195|192|201|158|180|200|192|173|183|181|176|189|182|171|182|158|193|178|164|152|160|169|163|189|140|160|154|165|139|167|159|159|157|154|154|155|167|120|158|169|127|138|152|123|127|115|129|127|114|116|109|125|95|90|114|90|99|85|102|96|82|81|59|91|91|74|91|82|72|84|79|72|65|68|62|72|73|61|54|68|67|58|56|59|41|54|47|55|57|32|48|70|52|50|49|42|43|48|47|36|38|34|38|33|40|30|34|29|29|34|27|28|32|35|38|29|39|40|33|33|24|35|25|21|29|33|27|20|28|21|17|29|23|18|17|27|19|26|21|19|21|24|15|26|21|16|15|19|23|20|33|21|16|20|18|15|19|19|14|10|17|15|26|19|19|18|25|16|21|17|18|14|19|17|17|13|19|19|23|18|14|26|21|19|11|23|16|16|17|8|16|14|22|19|22|14|11|22|14|15|10|15|17|16|21|22|18|11|13|16|18|16|13|23|20|23|23|23|14|13|19|22|21|12|27|11|11|11|15|15|20|15|21|16|10|12|15|22|20|16|17|13|9|12|12|13|21|14|12|19|8|12|15|7|20|12|12|15|22|14|16|26|22|22|23|20|22|18|18|16|15|20|22|16|25|20|23|20|25|30|34|25|15|20|20|20|26|14|29|31|27|26|24|24|22|21|15|15|28|23|15|19|24|18|28|18|18|18|20|10|27|12|18|12|10|12|23|22|15|16|17|16|12|16|15|15|20|18|15|20|15|9|14|19|9|13|16|10|13|6|23|20|5|12|19|15|17|16|15|14|19|14|11|8|12|13|14|14|12|8|18|14|11|12|13|16|10|18|11|11|9|11|17|11|8|9|6|7|11|10|6|7|4|6|6|8|3|7|8|4|4|3|4|3|2|1|0|1|0|3|0|0|1|2|1|0|1|0|0|1</HistCounts>
      </HistItem>
    </Histograms>
    <Metadata>
      <MDI key="STATISTICS_MAXIMUM">10314</MDI>
      <MDI key="STATISTICS_MEAN">1318.1093788032</MDI>
      <MDI key="STATISTICS_MINIMUM">0</MDI>
      <MDI key="STATISTICS_STDDEV">2113.4619708592</MDI>
      <MDI key="STATISTICS_VALID_PERCENT">100</MDI>
    </Metadata>
  </PAMRasterBand>
</PAMDataset>
